pymodoro
