Metadata-Version: 1.0
Name: pymodoro
Version: 1.1.4
Summary: It's a command line pomodoro timer
Home-page: https://github.com/rogeralmeida/pomodoro
Author: Roger Almeida
Author-email: roger.eduardo@gmail.com
License: MIT
Keywords: pomodoro technique timer application cli command line tool
Platform: UNKNOWN
